databend-1.2.810.dist-info/METADATA
databend-1.2.810.dist-info/WHEEL
databend/__init__.py
databend/databend.abi3.so
databend-1.2.810.dist-info/RECORD
